scoutos/__init__.py
scoutos/client.py
scoutos/collections/__init__.py
scoutos/collections/client.py
scoutos/core/__init__.py
scoutos/core/api_error.py
scoutos/core/client_wrapper.py
scoutos/core/datetime_utils.py
scoutos/core/file.py
scoutos/core/http_client.py
scoutos/core/jsonable_encoder.py
scoutos/core/pydantic_utilities.py
scoutos/core/query_encoder.py
scoutos/core/remove_none_from_dict.py
scoutos/core/request_options.py
scoutos/core/serialization.py
scoutos/documents/__init__.py
scoutos/documents/client.py
scoutos/documents/types/__init__.py
scoutos/documents/types/documents_create_request.py
scoutos/environment.py
scoutos/errors/__init__.py
scoutos/errors/unprocessable_entity_error.py
scoutos/py.typed
scoutos/types/__init__.py
scoutos/types/actor.py
scoutos/types/actor_type.py
scoutos/types/api_key_identity.py
scoutos/types/app_run_completed_data.py
scoutos/types/app_run_failed_data.py
scoutos/types/app_run_started_data.py
scoutos/types/block_run_completed.py
scoutos/types/block_run_completed_data.py
scoutos/types/block_run_completed_environment.py
scoutos/types/block_run_failed.py
scoutos/types/block_run_failed_data.py
scoutos/types/block_run_failed_environment.py
scoutos/types/block_run_started.py
scoutos/types/block_run_started_data.py
scoutos/types/block_run_started_environment.py
scoutos/types/collection.py
scoutos/types/collection_config_input.py
scoutos/types/collection_config_input_columns_item.py
scoutos/types/collection_config_output.py
scoutos/types/collection_config_output_columns_item.py
scoutos/types/column_type_item_check_box.py
scoutos/types/column_type_item_json.py
scoutos/types/column_type_item_number.py
scoutos/types/column_type_item_number_default_value.py
scoutos/types/column_type_item_number_max_value.py
scoutos/types/column_type_item_number_min_value.py
scoutos/types/column_type_item_select.py
scoutos/types/column_type_item_text_long.py
scoutos/types/column_type_item_text_short.py
scoutos/types/content_type.py
scoutos/types/document.py
scoutos_test-0.1.11.dist-info/METADATA
scoutos_test-0.1.11.dist-info/WHEEL
scoutos_test-0.1.11.dist-info/RECORD
